connect_resume_extractor-0.1.3.dist-info/licenses/LICENSE
resume_extractor/__init__.py
resume_extractor/cli.py
resume_extractor/db.py
resume_extractor/extraction.py
resume_extractor/resources/normalized_branches.jsonl
resume_extractor/resources/normalized_colleges.jsonl
connect_resume_extractor-0.1.3.dist-info/METADATA
connect_resume_extractor-0.1.3.dist-info/WHEEL
connect_resume_extractor-0.1.3.dist-info/entry_points.txt
connect_resume_extractor-0.1.3.dist-info/top_level.txt
connect_resume_extractor-0.1.3.dist-info/RECORD
