Metadata-Version: 2.4
Name: connect-resume-extractor
Version: 0.1.3
Summary: A Python package to extract resume data (college, branch, mobile, degree, passout year, LinkedIn) from PDFs.
Author-email: Reddy Rohith <reddyrohith20061902@gmail.com>
Requires-Python: >=3.8
License-File: LICENSE
Requires-Dist: pandas
Requires-Dist: PyMuPDF
Dynamic: license-file
